ccxxv
