Metadata-Version: 1.1
Name: ccxxv
Version: 0.1.4
Summary: Crossword solving assistant
Home-page: https://github.com/paul-butcher/ccxxv
Author: Paul Butcher
Author-email: UNKNOWN
License: LGPL-3
Platform: UNKNOWN
Classifier: Development Status :: 3 - Alpha
Classifier: Intended Audience :: Developers
Classifier: Topic :: Games/Entertainment :: Puzzle Games
Classifier: License :: OSI Approved :: GNU Lesser General Public License v3 (LGPLv3)
Classifier: Programming Language :: Python :: 2.7
